wadi/__init__.py
wadi/api_utils.py
wadi/base.py
wadi/dataobject.py
wadi/documentation_helpers.py
wadi/filereader.py
wadi/harmonizer.py
wadi/infotable.py
wadi/mapper.py
wadi/unitconverter.py
wadi/utils.py
wadi/mapping_data/atoms.csv
wadi/mapping_data/default_feature_map.json
wadi/mapping_data/ions.csv
wadi/mapping_data/other_than_concentrations.csv
wadi-0.2.dist-info/LICENSE
wadi-0.2.dist-info/METADATA
wadi-0.2.dist-info/WHEEL
wadi-0.2.dist-info/top_level.txt
wadi-0.2.dist-info/RECORD
