Metadata-Version: 2.1
Name: wadi
Version: 0.2
Summary: Generic importer for water quality data of the (Dutch) water laboratory
Home-page: https://github.com/KWR-Water/wadi
Author: KWR Water Research Institute
Author-email: martin.korevaar@kwrwater.nl, martin.van.der.schans@kwrwater.nl
License: MIT
Project-URL: Source, https://github.com/KWR-Water/wadi
Project-URL: Documentation, http://wadi.readthedocs.io/en/latest/
Project-URL: Tracker, https://github.com/KWR-Water/wadi/issues
Project-URL: Help, https://github.com/KWR-Water/wadi/issues
Classifier: Development Status :: 4 - Beta
Classifier: Intended Audience :: Science/Research
Classifier: Intended Audience :: Other Audience
Classifier: License :: OSI Approved :: MIT License
Classifier: Programming Language :: Python :: 3.8
Classifier: Programming Language :: Python :: 3.9
Classifier: Programming Language :: Python :: 3.10
Classifier: Programming Language :: Python :: 3.11
Classifier: Topic :: Scientific/Engineering :: Hydrology
Requires-Python: >=3.8
License-File: LICENSE
Requires-Dist: pandas (<2,>=1)
Requires-Dist: pint
Requires-Dist: requests
Requires-Dist: molmass
Requires-Dist: openpyxl (>=3.0.0)
Requires-Dist: googletrans (==3.1.0a0)
Requires-Dist: fuzzywuzzy
Requires-Dist: levenshtein (>=0.20.9)
Requires-Dist: python-Levenshtein (>=0.20.9)
